pywrapped_orbslam3/__init__.py
pywrapped_orbslam3/_core.cpython-312-x86_64-linux-gnu.so
pywrapped_orbslam3/_version.py
pywrapped_orbslam3.libs/libDBoW2-3d7fb4c2.so
pywrapped_orbslam3.libs/libGLEW-cc680dfb.so.2.0.0
pywrapped_orbslam3.libs/libGLU-ff1477cc.so.1.3.1
pywrapped_orbslam3.libs/libGLX-c14481bc.so.0.0.0
pywrapped_orbslam3.libs/libGLdispatch-64b28464.so.0.0.0
pywrapped_orbslam3.libs/libORB_SLAM3-230e1ceb.so
pywrapped_orbslam3.libs/libOpenGL-4c5f8d52.so.0.0.0
pywrapped_orbslam3.libs/libQt5Core-832803ac.so.5.15.3
pywrapped_orbslam3.libs/libQt5Gui-30d34e12.so.5.15.3
pywrapped_orbslam3.libs/libQt5Widgets-2e92b9ef.so.5.15.3
pywrapped_orbslam3.libs/libblkid-a9167753.so.1.1.0
pywrapped_orbslam3.libs/libboost_date_time-bfc31cd3.so.1.66.0
pywrapped_orbslam3.libs/libboost_filesystem-38deced9.so.1.66.0
pywrapped_orbslam3.libs/libboost_iostreams-5e889418.so.1.66.0
pywrapped_orbslam3.libs/libboost_regex-2b30dfd4.so.1.66.0
pywrapped_orbslam3.libs/libboost_serialization-3aa46b41.so.1.66.0
pywrapped_orbslam3.libs/libboost_system-69a6c43e.so.1.66.0
pywrapped_orbslam3.libs/libbz2-a1e77c99.so.1.0.6
pywrapped_orbslam3.libs/libcap-16fca4d2.so.2.48
pywrapped_orbslam3.libs/libcrypto-bdaed0ea.so.1.1.1k
pywrapped_orbslam3.libs/libdouble-conversion-b406f6fa.so.3.1.5
pywrapped_orbslam3.libs/libflann_cpp-357c504e.so.1.9.1
pywrapped_orbslam3.libs/libfreetype-2f3b32b6.so.6.16.1
pywrapped_orbslam3.libs/libg2o-0f087338.so
pywrapped_orbslam3.libs/libgcrypt-a1b5cc4c.so.20.2.5
pywrapped_orbslam3.libs/libgomp-870cb1d0.so.1.0.0
pywrapped_orbslam3.libs/libgpg-error-d4e115d0.so.0.24.2
pywrapped_orbslam3.libs/libgraphite2-a2b39163.so.3.0.1
pywrapped_orbslam3.libs/libharfbuzz-26b3d829.so.0.10705.0
pywrapped_orbslam3.libs/libicudata-05640f77.so.60.3
pywrapped_orbslam3.libs/libicui18n-4fcc01ea.so.60.3
pywrapped_orbslam3.libs/libicuuc-14201aad.so.60.3
pywrapped_orbslam3.libs/libjbig-2504a0c3.so.2.1
pywrapped_orbslam3.libs/libjpeg-e87d2658.so.62.2.0
pywrapped_orbslam3-1.4.6.dist-info/METADATA
pywrapped_orbslam3-1.4.6.dist-info/WHEEL
pywrapped_orbslam3-1.4.6.dist-info/top_level.txt
pywrapped_orbslam3-1.4.6.dist-info/RECORD
pywrapped_orbslam3-1.4.6.dist-info/licenses/LICENSE
