Metadata-Version: 2.4
Name: pywrapped_orbslam3
Version: 1.4.6
Summary: SLAM and Global VO module for VNAV project
Maintainer-email: "Alex S." <savaalexandru562@gmail.com>
License:                     GNU GENERAL PUBLIC LICENSE
Project-URL: Bug Tracker, https://github.com/AlexandruRO45/ORB-SLAM3/issues
Project-URL: Source, https://github.com/AlexandruRO45/ORB-SLAM3/
Classifier: Intended Audience :: Developers
Classifier: License :: OSI Approved :: GNU General Public License v3 or later (GPLv3+)
Classifier: Programming Language :: C++
Classifier: Programming Language :: Python :: 3
Classifier: Programming Language :: Python :: 3 :: Only
Classifier: Programming Language :: Python :: 3.11
Classifier: Programming Language :: Python :: 3.12
Requires-Python: >=3.11
License-File: LICENSE
Requires-Dist: numpy
Requires-Dist: opencv-python
Provides-Extra: test
Requires-Dist: pytest>=6.0; extra == "test"
Requires-Dist: pyyaml>=5.4; extra == "test"
Dynamic: license-file
